rnajena_sugar-1.0.0.dist-info/licenses/LICENSE
sugar/__init__.py
sugar/scripts.py
sugar/_io/__init__.py
sugar/_io/clustal.py
sugar/_io/embl.py
sugar/_io/fasta.py
sugar/_io/genbank.py
sugar/_io/gff.py
sugar/_io/main.py
sugar/_io/sjson.py
sugar/_io/stockholm.py
sugar/_io/util.py
sugar/_io/tab/__init__.py
sugar/_io/tab/blast.py
sugar/_io/tab/core.py
sugar/_io/tab/infernal.py
sugar/_io/tab/mmseqs.py
sugar/_io/tab/xsv.py
sugar/core/__init__.py
sugar/core/_adapter.py
sugar/core/cane.py
sugar/core/fts.py
sugar/core/meta.py
sugar/core/seq.py
sugar/core/util.py
sugar/data/__init__.py
sugar/data/data_gcode/convert.py
sugar/data/data_gcode/gc.json
sugar/data/data_gcode/gc.prt
sugar/data/data_submat/BLOSUM100
sugar/data/data_submat/BLOSUM100.50
sugar/data/data_submat/BLOSUM30
sugar/data/data_submat/BLOSUM30.50
sugar/data/data_submat/BLOSUM35
sugar/data/data_submat/BLOSUM35.50
sugar/data/data_submat/BLOSUM40
sugar/data/data_submat/BLOSUM40.50
sugar/data/data_submat/BLOSUM45
sugar/data/data_submat/BLOSUM45.50
sugar/data/data_submat/BLOSUM50
sugar/data/data_submat/BLOSUM50.50
sugar/data/data_submat/BLOSUM55
sugar/data/data_submat/BLOSUM55.50
sugar/data/data_submat/BLOSUM60
sugar/data/data_submat/BLOSUM60.50
sugar/data/data_submat/BLOSUM62
sugar/data/data_submat/BLOSUM62.50
sugar/data/data_submat/BLOSUM65
sugar/data/data_submat/BLOSUM65.50
sugar/data/data_submat/BLOSUM70
sugar/data/data_submat/BLOSUM70.50
sugar/data/data_submat/BLOSUM75
sugar/data/data_submat/BLOSUM75.50
sugar/data/data_submat/BLOSUM80
sugar/data/data_submat/BLOSUM80.50
sugar/data/data_submat/BLOSUM85
sugar/data/data_submat/BLOSUM85.50
sugar/data/data_submat/BLOSUM90
sugar/data/data_submat/BLOSUM90.50
sugar/data/data_submat/BLOSUMN
sugar/data/data_submat/BLOSUMN.50
sugar/data/data_submat/DAYHOFF
sugar/data/data_submat/GONNET
sugar/data/data_submat/IDENTITY
sugar/data/data_submat/MATCH
sugar/data/data_submat/NUC
sugar/data/data_submat/NUC.4.2
sugar/data/data_submat/NUC.4.4
sugar/data/data_submat/PAM10
sugar/data/data_submat/PAM100
sugar/data/data_submat/PAM110
rnajena_sugar-1.0.0.dist-info/METADATA
rnajena_sugar-1.0.0.dist-info/WHEEL
rnajena_sugar-1.0.0.dist-info/entry_points.txt
rnajena_sugar-1.0.0.dist-info/top_level.txt
rnajena_sugar-1.0.0.dist-info/RECORD
