Metadata-Version: 2.4
Name: rnajena-sugar
Version: 1.0.0
Summary: A Python framework for bioinformatics
Author: Tom Eulenfeld
License-Expression: MIT
Project-URL: Homepage, https://github.com/rnajena/sugar
Project-URL: Bug Tracker, https://github.com/rnajena/sugar/issues
Keywords: bioinformatics,RNA,DNA,sequence,fasta,genbank,stockholm,blast,entrez,index
Classifier: Intended Audience :: Science/Research
Classifier: Intended Audience :: Education
Classifier: Operating System :: OS Independent
Classifier: Programming Language :: Python :: 3
Classifier: Topic :: Scientific/Engineering :: Bio-Informatics
Requires-Python: >=3.11
License-File: LICENSE
Requires-Dist: binarysearchfile
Requires-Dist: dna_features_viewer_lite
Requires-Dist: matplotlib
Requires-Dist: pandas
Requires-Dist: platformdirs
Requires-Dist: pytest
Requires-Dist: requests
Requires-Dist: seaborn
Dynamic: description
Dynamic: description-content-type
Dynamic: license-file
